[
    {
        "key": "dbln",
        "value": "%7B%2261557976184172%22%3A%22YzwQZfpo%22%7D",
        "domain": "facebook.com",
        "path": "/login/device-based/",
        "hostOnly": false,
        "creation": "2024-06-11T02:39:02.864Z",
        "lastAccessed": "2024-06-11T02:39:02.864Z"
    },
    {
        "key": "sb",
        "value": "AMhWZhGsW559Vs3zy3dtit16",
        "domain": "facebook.com",
        "path": "/",
        "hostOnly": false,
        "creation": "2024-06-11T02:39:02.864Z",
        "lastAccessed": "2024-06-11T02:39:02.865Z"
    },
    {
        "key": "datr",
        "value": "RAlXZuuIe0hMnhbulvKCe1OA",
        "domain": "facebook.com",
        "path": "/",
        "hostOnly": false,
        "creation": "2024-06-11T02:39:02.865Z",
        "lastAccessed": "2024-06-11T02:39:02.865Z"
    },
    {
        "key": "ps_n",
        "value": "1",
        "domain": "facebook.com",
        "path": "/",
        "hostOnly": false,
        "creation": "2024-06-11T02:39:02.865Z",
        "lastAccessed": "2024-06-11T02:39:02.865Z"
    },
    {
        "key": "ps_l",
        "value": "1",
        "domain": "facebook.com",
        "path": "/",
        "hostOnly": false,
        "creation": "2024-06-11T02:39:02.865Z",
        "lastAccessed": "2024-06-11T02:39:02.865Z"
    },
    {
        "key": "dpr",
        "value": "1.5403207540512085",
        "domain": "facebook.com",
        "path": "/",
        "hostOnly": false,
        "creation": "2024-06-11T02:39:02.865Z",
        "lastAccessed": "2024-06-11T02:39:02.865Z"
    },
    {
        "key": "vpd",
        "value": "v1%3B718x412x1.4009960889816284",
        "domain": "facebook.com",
        "path": "/",
        "hostOnly": false,
        "creation": "2024-06-11T02:39:02.865Z",
        "lastAccessed": "2024-06-11T02:39:02.865Z"
    },
    {
        "key": "m_pixel_ratio",
        "value": "1.4009960889816284",
        "domain": "facebook.com",
        "path": "/",
        "hostOnly": false,
        "creation": "2024-06-11T02:39:02.865Z",
        "lastAccessed": "2024-06-11T02:39:02.865Z"
    },
    {
        "key": "wd",
        "value": "515x897",
        "domain": "facebook.com",
        "path": "/",
        "hostOnly": false,
        "creation": "2024-06-11T02:39:02.865Z",
        "lastAccessed": "2024-06-11T02:39:02.865Z"
    },
    {
        "key": "locale",
        "value": "en_GB",
        "domain": "facebook.com",
        "path": "/",
        "hostOnly": false,
        "creation": "2024-06-11T02:39:02.865Z",
        "lastAccessed": "2024-06-11T02:39:02.865Z"
    },
    {
        "key": "wl_cbv",
        "value": "v2%3Bclient_version%3A2521%3Btimestamp%3A1718067587",
        "domain": "facebook.com",
        "path": "/",
        "hostOnly": false,
        "creation": "2024-06-11T02:39:02.865Z",
        "lastAccessed": "2024-06-11T02:39:02.865Z"
    },
    {
        "key": "c_user",
        "value": "61557976184172",
        "domain": "facebook.com",
        "path": "/",
        "hostOnly": false,
        "creation": "2024-06-11T02:39:02.865Z",
        "lastAccessed": "2024-06-11T02:39:02.865Z"
    },
    {
        "key": "xs",
        "value": "16%3AMhRxZdTlgjdk8Q%3A2%3A1718073517%3A-1%3A3362",
        "domain": "facebook.com",
        "path": "/",
        "hostOnly": false,
        "creation": "2024-06-11T02:39:02.865Z",
        "lastAccessed": "2024-06-11T02:39:02.866Z"
    },
    {
        "key": "fr",
        "value": "1q4BA29uXXRhn2eT0.AWXNAU5PLhFR2dZRWIK2B9IZaxo.BmX8_U..AAA.0.0.BmZ7is.AWXZezBl9Fg",
        "domain": "facebook.com",
        "path": "/",
        "hostOnly": false,
        "creation": "2024-06-11T02:39:02.866Z",
        "lastAccessed": "2024-06-11T02:39:02.866Z"
    },
    {
        "key": "m_page_voice",
        "value": "61557976184172",
        "domain": "facebook.com",
        "path": "/",
        "hostOnly": false,
        "creation": "2024-06-11T02:39:02.866Z",
        "lastAccessed": "2024-06-11T02:39:02.866Z"
    }
]
