[
    {
        "key": "dbln",
        "value": "%7B%2261551812203552%22%3A%22t0lqzPVb%22%2C%2261555886833462%22%3A%22uns5aATQ%22%7D",
        "domain": "facebook.com",
        "path": "/login/device-based/",
        "hostOnly": false,
        "creation": "2024-06-07T18:12:43.930Z",
        "lastAccessed": "2024-06-07T18:12:43.930Z"
    },
    {
        "key": "datr",
        "value": "vfD1ZDVSFFy4gfu-s9A8Iw8F",
        "domain": "facebook.com",
        "path": "/",
        "hostOnly": false,
        "creation": "2024-06-07T18:12:43.931Z",
        "lastAccessed": "2024-06-07T18:12:43.931Z"
    },
    {
        "key": "sb",
        "value": "vfD1ZGbqYU4Er8D4aQePaUmb",
        "domain": "facebook.com",
        "path": "/",
        "hostOnly": false,
        "creation": "2024-06-07T18:12:43.931Z",
        "lastAccessed": "2024-06-07T18:12:43.931Z"
    },
    {
        "key": "ps_n",
        "value": "1",
        "domain": "facebook.com",
        "path": "/",
        "hostOnly": false,
        "creation": "2024-06-07T18:12:43.931Z",
        "lastAccessed": "2024-06-07T18:12:43.931Z"
    },
    {
        "key": "ps_l",
        "value": "1",
        "domain": "facebook.com",
        "path": "/",
        "hostOnly": false,
        "creation": "2024-06-07T18:12:43.931Z",
        "lastAccessed": "2024-06-07T18:12:43.931Z"
    },
    {
        "key": "m_pixel_ratio",
        "value": "2",
        "domain": "facebook.com",
        "path": "/",
        "hostOnly": false,
        "creation": "2024-06-07T18:12:43.931Z",
        "lastAccessed": "2024-06-07T18:12:43.931Z"
    },
    {
        "key": "locale",
        "value": "en_US",
        "domain": "facebook.com",
        "path": "/",
        "hostOnly": false,
        "creation": "2024-06-07T18:12:43.931Z",
        "lastAccessed": "2024-06-07T18:12:43.931Z"
    },
    {
        "key": "vpd",
        "value": "v1%3B559x360x2",
        "domain": "facebook.com",
        "path": "/",
        "hostOnly": false,
        "creation": "2024-06-07T18:12:43.931Z",
        "lastAccessed": "2024-06-07T18:12:43.931Z"
    },
    {
        "key": "wl_cbv",
        "value": "v2%3Bclient_version%3A2524%3Btimestamp%3A1717783511",
        "domain": "facebook.com",
        "path": "/",
        "hostOnly": false,
        "creation": "2024-06-07T18:12:43.931Z",
        "lastAccessed": "2024-06-07T18:12:43.931Z"
    },
    {
        "key": "dpr",
        "value": "2.1988937854766846",
        "domain": "facebook.com",
        "path": "/",
        "hostOnly": false,
        "creation": "2024-06-07T18:12:43.931Z",
        "lastAccessed": "2024-06-07T18:12:43.931Z"
    },
    {
        "key": "wd",
        "value": "891x1384",
        "domain": "facebook.com",
        "path": "/",
        "hostOnly": false,
        "creation": "2024-06-07T18:12:43.931Z",
        "lastAccessed": "2024-06-07T18:12:43.931Z"
    },
    {
        "key": "c_user",
        "value": "100052250385822",
        "domain": "facebook.com",
        "path": "/",
        "hostOnly": false,
        "creation": "2024-06-07T18:12:43.931Z",
        "lastAccessed": "2024-06-07T18:12:43.931Z"
    },
    {
        "key": "xs",
        "value": "36%3At8ruViHbPiYIBA%3A2%3A1717783927%3A-1%3A3594",
        "domain": "facebook.com",
        "path": "/",
        "hostOnly": false,
        "creation": "2024-06-07T18:12:43.931Z",
        "lastAccessed": "2024-06-07T18:12:43.931Z"
    },
    {
        "key": "fr",
        "value": "0CmTajLdZdm2qgYOr.AWXV2krE1UmHIZv5WjRYNUgVY_8.BmYz8G..AAA.0.0.BmY02N.AWUQ9dliufY",
        "domain": "facebook.com",
        "path": "/",
        "hostOnly": false,
        "creation": "2024-06-07T18:12:43.931Z",
        "lastAccessed": "2024-06-07T18:12:43.931Z"
    }
]
